LordMedia/__init__.py
LordMedia/mediainfo/__init__.py
LordMedia/mediainfo/lib/__init__.py
LordMedia/mediainfo/lib/MediaInfoLib/mac/__init__.py
LordMedia/mediainfo/lib/MediaInfoLib/win/__init__.py
LordMedia-2023.5.13.1.dist-info/METADATA
LordMedia-2023.5.13.1.dist-info/WHEEL
LordMedia-2023.5.13.1.dist-info/top_level.txt
LordMedia-2023.5.13.1.dist-info/RECORD
