Metadata-Version: 2.1
Name: LordMedia
Version: 2023.5.13.1
Summary: LordMedia by LordBex
Author-email: lordbex <lordibex@protonmail.com>
Maintainer-email: lordbex <lordibex@protonmail.com>
Project-URL: homepage, https://git.lordbex.xyz/PipModule/LordMedia
Project-URL: repository, https://git.lordbex.xyz/PipModule/LordMedia
Requires-Python: >=3.10
Requires-Dist: pymediainfo
Requires-Dist: regex
Requires-Dist: LordFile
